README.rst
setup.cfg
setup.py
ordered_map/__init__.py
ordered_map/cli.py
ordered_map/ordered_map.py
ordered_map.egg-info/PKG-INFO
ordered_map.egg-info/SOURCES.txt
ordered_map.egg-info/dependency_links.txt
ordered_map.egg-info/entry_points.txt
ordered_map.egg-info/requires.txt
ordered_map.egg-info/top_level.txt