Metadata-Version: 1.1
Name: ordered-map
Version: 0.0.1
Summary: Ordered map parser and writer..
Home-page: https://github.com/jfjlaros/ordered-map
Author: Jeroen F.J. Laros
Author-email: jlaros@fixedpoint.nl
License: MIT
Platform: UNKNOWN
Classifier: Intended Audience :: Developers
Classifier: Intended Audience :: Science/Research
Classifier: Operating System :: OS Independent
Classifier: Programming Language :: Python :: 3
Classifier: Topic :: Scientific/Engineering
